odoo/addons/ddmrp_history/README.rst
odoo/addons/ddmrp_history/__init__.py
odoo/addons/ddmrp_history/__manifest__.py
odoo/addons/ddmrp_history/demo/ddmrp.history.csv
odoo/addons/ddmrp_history/i18n/ddmrp_history.pot
odoo/addons/ddmrp_history/i18n/fr.po
odoo/addons/ddmrp_history/models/__init__.py
odoo/addons/ddmrp_history/models/ddmrp_history.py
odoo/addons/ddmrp_history/models/stock_warehouse_orderpoint.py
odoo/addons/ddmrp_history/readme/CONTRIBUTORS.rst
odoo/addons/ddmrp_history/readme/CREDITS.rst
odoo/addons/ddmrp_history/readme/DESCRIPTION.rst
odoo/addons/ddmrp_history/readme/HISTORY.rst
odoo/addons/ddmrp_history/readme/INSTALL.rst
odoo/addons/ddmrp_history/readme/USAGE.rst
odoo/addons/ddmrp_history/security/ir.model.access.csv
odoo/addons/ddmrp_history/static/description/icon.png
odoo/addons/ddmrp_history/static/description/index.html
odoo/addons/ddmrp_history/tests/__init__.py
odoo/addons/ddmrp_history/tests/test_ddmrp_history.py
odoo/addons/ddmrp_history/views/ddmrp_history_view.xml
odoo/addons/ddmrp_history/views/stock_warehouse_orderpoint_view.xml
odoo11_addon_ddmrp_history-11.0.1.0.1.99.dev4.dist-info/METADATA
odoo11_addon_ddmrp_history-11.0.1.0.1.99.dev4.dist-info/WHEEL
odoo11_addon_ddmrp_history-11.0.1.0.1.99.dev4.dist-info/top_level.txt
odoo11_addon_ddmrp_history-11.0.1.0.1.99.dev4.dist-info/RECORD
